geomapi/__init__.py
geomapi/nodes/__init__.py
geomapi/nodes/bimnode.py
geomapi/nodes/imagenode.py
geomapi/nodes/linesetnode.py
geomapi/nodes/meshnode.py
geomapi/nodes/node.py
geomapi/nodes/orthonode.py
geomapi/nodes/panonode.py
geomapi/nodes/pointcloudnode.py
geomapi/nodes/setnode.py
geomapi/tools/__init__.py
geomapi/tools/alignmenttools/__init__.py
geomapi/tools/alignmenttools/match.py
geomapi/tools/alignmenttools/params.py
geomapi/tools/combinationtools/__init__.py
geomapi/tools/inspectiontools/__init__.py
geomapi/tools/machinelearningtools/__init__.py
geomapi/tools/progresstools/__init__.py
geomapi/tools/validationtools/__init__.py
geomapi/utils/__init__.py
geomapi/utils/cadutils.py
geomapi/utils/geometryutils.py
geomapi/utils/geospatialutils.py
geomapi/utils/imageutils.py
geomapi-1.0.0.dist-info/licenses/LICENSE
tests/__init__.py
tests/data_loader_indoor_site.py
tests/data_loader_parking.py
tests/data_loader_railway.py
tests/data_loader_road.py
tests/test_bimnode.py
tests/test_cadutils.py
tests/test_geometryutils.py
tests/test_geospatialutils.py
tests/test_imageutils.py
tests/test_imgnode.py
tests/test_linesetnode.py
tests/test_meshnode.py
tests/test_node.py
tests/test_orthonode.py
tests/test_panonode.py
tests/test_pointcloudnode.py
tests/test_setnode.py
tests/test_tools.py
tests/test_utils.py
geomapi-1.0.0.dist-info/METADATA
geomapi-1.0.0.dist-info/WHEEL
geomapi-1.0.0.dist-info/top_level.txt
geomapi-1.0.0.dist-info/RECORD
