Metadata-Version: 2.4
Name: geomapi
Version: 1.0.0
Summary: A standard library to manage geomatic data
Home-page: https://ku-leuven-geomatics.github.io/geomapi/index.html
Author: Bassier M., De Geyter S., De Winter H., Vermandere J. @ Geomatics KU Leuven
License: MIT
Keywords: Geomatics,alignment,monitoring,validation,progress,point clouds,computer vision,deep learning
Classifier: Programming Language :: Python :: 3
Classifier: License :: OSI Approved :: MIT License
Classifier: Operating System :: OS Independent
Requires-Python: <=3.12
License-File: LICENSE
Requires-Dist: open3d
Requires-Dist: opencv-python
Requires-Dist: pye57
Requires-Dist: numpy
Requires-Dist: numpy-quaternion
Requires-Dist: rdflib
Requires-Dist: typing_extensions
Requires-Dist: matplotlib
Requires-Dist: ifcopenshell
Requires-Dist: scipy
Requires-Dist: pillow
Requires-Dist: XlsxWriter
Requires-Dist: trimesh
Requires-Dist: python-fcl
Requires-Dist: pandas
Requires-Dist: lark
Requires-Dist: colour
Requires-Dist: laspy
Requires-Dist: lazrs
Requires-Dist: scikit-learn
Requires-Dist: ezdxf
Requires-Dist: pyvista
Requires-Dist: shapely
Requires-Dist: pyproj
Dynamic: license-file
